cv_smart_house_module_motion_detection/__init__.py
cv_smart_house_module_motion_detection/processing.py
cv_smart_house_module_motion_detection/t.proto
cv_smart_house_module_motion_detection-0.1.9.dist-info/METADATA
cv_smart_house_module_motion_detection-0.1.9.dist-info/WHEEL
cv_smart_house_module_motion_detection-0.1.9.dist-info/RECORD
