Metadata-Version: 2.1
Name: cv_smart_house_module_motion_detection
Version: 0.1.9
Summary: 
Author: Mykyta Krukovskyi
Author-email: mykyta.krukovskyi@gmail.com
Requires-Python: >=3.10,<4.0
Classifier: Programming Language :: Python :: 3
Classifier: Programming Language :: Python :: 3.10
Classifier: Programming Language :: Python :: 3.11
Classifier: Programming Language :: Python :: 3.12
Requires-Dist: numpy (>=1.26.4,<2.0.0)
Requires-Dist: opencv-python (>=4.9.0.80,<5.0.0.0)
